athena_federation/__init__.py
athena_federation/athena_data_source.py
athena_federation/batch_writer.py
athena_federation/lambda_handler.py
athena_federation/main.py
athena_federation/models.py
athena_federation/py.typed
athena_federation/sdk.py
athena_federation/utils.py
athena_federation-0.1.6.dist-info/LICENSE
athena_federation-0.1.6.dist-info/METADATA
athena_federation-0.1.6.dist-info/WHEEL
athena_federation-0.1.6.dist-info/RECORD
