Metadata-Version: 2.1
Name: athena-federation
Version: 0.1.6
Summary: Unofficial Python SDK for Athena Federation
Home-page: https://github.com/dacort/athena-federation-python-sdk
License: APACHE
Author: Damon P. Cortesi
Author-email: d.lifehacker@gmail.com
Requires-Python: >=3.12,<4.0
Classifier: License :: Other/Proprietary License
Classifier: Programming Language :: Python :: 3
Classifier: Programming Language :: Python :: 3.12
Requires-Dist: importlib-metadata (<5.0.0)
Requires-Dist: pyarrow (==17.0.0)
Requires-Dist: pyarrow-stubs (>=10.0.1.9,<11.0.0.0)
Requires-Dist: pytest-watcher (>=0.4.2,<0.5.0)
Requires-Dist: smart-open (==7.0.4)
Project-URL: Documentation, https://github.com/dacort/athena-federation-python-sdk
Project-URL: Repository, https://github.com/dacort/athena-federation-python-sdk
